Metadata-Version: 2.1
Name: BinPackerPro
Version: 0.0.9
Summary: bin packer pro
Author: Shaik Arshad
Author-email: smdar7@example.com
License: MIT
Classifier: Programming Language :: Python :: 3
Classifier: License :: OSI Approved :: MIT License
Classifier: Operating System :: OS Independent
Classifier: Programming Language :: Python :: 3.6
License-File: LICENSE
